pycon25cvosbpapp/__init__.py
pycon25cvosbpapp/__main__.py
pycon25cvosbpapp/py.typed
pycon25cvosbpapp/pycon25cvosbpapp.py
pycon25cvosbpapp-0.2.0.dist-info/WHEEL
pycon25cvosbpapp-0.2.0.dist-info/entry_points.txt
pycon25cvosbpapp-0.2.0.dist-info/METADATA
pycon25cvosbpapp-0.2.0.dist-info/RECORD
