Metadata-Version: 2.3
Name: pycon25cvosbpapp
Version: 0.2.0
Summary: PyCon Demo app
Author: Carlo van Overbeek
Author-email: Carlo van Overbeek <cvanoverbeek@schubergphilis.com>
Classifier: License :: OSI Approved :: Apache Software License
Classifier: Programming Language :: Python :: 3.12
Requires-Dist: pycon25cvosbp>=0.1.0
Requires-Python: >=3.12
